energyplus_service/__about__.py
energyplus_service/__init__.py
energyplus_service/__main__.py
energyplus_service/cli/__init__.py
energyplus_service-0.0.1.dist-info/METADATA
energyplus_service-0.0.1.dist-info/WHEEL
energyplus_service-0.0.1.dist-info/entry_points.txt
energyplus_service-0.0.1.dist-info/licenses/LICENSE.txt
energyplus_service-0.0.1.dist-info/RECORD
