Metadata-Version: 2.3
Name: energyplus-service
Version: 0.0.1
Summary: A simple flask EnergyPlus service
Project-URL: Documentation, https://github.com/jasondegraw/energyplus-service#readme
Project-URL: Issues, https://github.com/jasondegraw/energyplus-service/issues
Project-URL: Source, https://github.com/jasondegraw/energyplus-service
Author-email: "Jason W. DeGraw" <jason.degraw@gmail.com>
License-Expression: BSD-3-Clause
License-File: LICENSE.txt
Classifier: Development Status :: 4 - Beta
Classifier: Programming Language :: Python
Classifier: Programming Language :: Python :: 3.8
Classifier: Programming Language :: Python :: 3.9
Classifier: Programming Language :: Python :: 3.10
Classifier: Programming Language :: Python :: 3.11
Classifier: Programming Language :: Python :: 3.12
Classifier: Programming Language :: Python :: Implementation :: CPython
Classifier: Programming Language :: Python :: Implementation :: PyPy
Requires-Python: >=3.8
Requires-Dist: click
Requires-Dist: flask
Requires-Dist: httpx
